ethereal/__init__.py
ethereal/accounts.py
ethereal/app.py
ethereal/base.py
ethereal/cache.py
ethereal/config.yml
ethereal/containers.py
ethereal/contracts.py
ethereal/etherscan.py
ethereal/facade.py
ethereal/networks.py
ethereal-0.1.9.dist-info/entry_points.txt
ethereal-0.1.9.dist-info/LICENSE
ethereal-0.1.9.dist-info/WHEEL
ethereal-0.1.9.dist-info/METADATA
ethereal-0.1.9.dist-info/RECORD
