Metadata-Version: 2.1
Name: ethereal
Version: 0.1.9
Summary: Ergonomic python tooling for web3
License: MIT
Author: Alex Euler
Author-email: 0xalexeuler@gmail.com
Requires-Python: >=3.10,<4.0
Classifier: License :: OSI Approved :: MIT License
Classifier: Programming Language :: Python :: 3
Classifier: Programming Language :: Python :: 3.10
Requires-Dist: PyYAML (>=6.0,<7.0)
Requires-Dist: click (>=8.1.3,<9.0.0)
Requires-Dist: dependency-injector (>=4.41.0,<5.0.0)
Requires-Dist: hdwallet (>=2.2.1,<3.0.0)
Requires-Dist: python-dateutil (>=2.8.2,<3.0.0)
Requires-Dist: web3 (>=6.1.0,<7.0.0)
